labpaper/__init__.py
labpaper/exporters/__init__.py
labpaper/exporters/base.py
labpaper/exporters/latexerror.py
labpaper/exporters/springer.py
labpaper/exporters/utils/__init__.py
labpaper/exporters/utils/address.py
labpaper/exporters/utils/affiliation.py
labpaper/exporters/utils/author.py
labpaper/exporters/utils/code_parser.py
labpaper/exporters/utils/resolvers.py
labpaper/filters/__init__.py
labpaper/preprocessors/__init__.py
labpaper/templates/nature/base.tex.j2
labpaper/templates/nature/contents.tex.j2
labpaper/templates/nature/display.tex.j2
labpaper/templates/nature/index.tex.j2
labpaper/texmf/__init__.py
labpaper/texmf/bibtex/bst/sn-apacite.bst
labpaper/texmf/bibtex/bst/sn-aps.bst
labpaper/texmf/bibtex/bst/sn-basic.bst
labpaper/texmf/bibtex/bst/sn-chicago.bst
labpaper/texmf/bibtex/bst/sn-mathphys-ay.bst
labpaper/texmf/bibtex/bst/sn-mathphys-num.bst
labpaper/texmf/bibtex/bst/sn-nature.bst
labpaper/texmf/bibtex/bst/sn-vancouver.bst
labpaper/texmf/tex/latex/sn-jnl/sn-jnl.cls
labpaper-1.0.21.dist-info/LICENSE
labpaper-1.0.21.dist-info/METADATA
labpaper-1.0.21.dist-info/WHEEL
labpaper-1.0.21.dist-info/entry_points.txt
labpaper-1.0.21.dist-info/top_level.txt
labpaper-1.0.21.dist-info/RECORD
