Metadata-Version: 2.2
Name: labpaper
Version: 1.0.21
Summary: LabPaper - A Jupyter notebook extension for exporting notebooks to academic papers.
Author-email: "Khris Griffis, Ph.D." <khris.griffis.phd@gmail.com>
Project-URL: Homepage, https://github.com/khrisgriffis/labpaper
Project-URL: Documentation, https://labpaper.readthedocs.io
Classifier: Programming Language :: Python :: 3
Classifier: License :: OSI Approved :: BSD License
Classifier: Operating System :: OS Independent
Classifier: Framework :: Jupyter
Classifier: Framework :: Jupyter :: JupyterLab
Requires-Python: >=3.11
License-File: LICENSE
Requires-Dist: nbconvert>=7.0.0
Requires-Dist: traitlets>=5.0.0
Requires-Dist: jupyter_core>=4.0.0
Requires-Dist: jinja2>=3.0.0
Requires-Dist: nbformat>=5.0.0
Requires-Dist: nameparser>=1.1.0
Requires-Dist: usaddress>=0.5.10
Provides-Extra: dev
Requires-Dist: pytest>=7.0; extra == "dev"
Requires-Dist: pytest-cov>=4.0; extra == "dev"
Requires-Dist: black>=22.0; extra == "dev"
Requires-Dist: isort>=5.0; extra == "dev"
Requires-Dist: flake8>=4.0; extra == "dev"
Requires-Dist: build>=0.7.0; extra == "dev"
Requires-Dist: twine>=4.0.0; extra == "dev"
Provides-Extra: docs
Requires-Dist: sphinx>=4.0; extra == "docs"
Requires-Dist: sphinx-rtd-theme>=1.0; extra == "docs"
Requires-Dist: myst-parser>=0.18; extra == "docs"
